Certifik8/__init__.py
Certifik8/constants/__init__.py
Certifik8/constants/help.txt
Certifik8/constants/menu.txt
Certifik8/constants/template.html
Certifik8/examples/Melissa Ribeiro Araujo.html
Certifik8/examples/Melissa Ribeiro Araujo.png
Certifik8/examples/__init__.py
Certifik8/examples/completa.xlsx
Certifik8/examples/exemplo-certificados.zip
Certifik8/examples/sem_coluna_informacoes.xlsx
Certifik8/examples/sem_decano.xlsx
Certifik8/examples/tabela_1_reg.xlsx
Certifik8/examples/vazia.xlsx
Certifik8/installer/__init__.py
Certifik8/installer/dependencies.sh
Certifik8/installer/installer.py
Certifik8/main.py
Certifik8/modules/__init__.py
Certifik8/modules/converter/__init__.py
Certifik8/modules/converter/html2pdf.py
Certifik8/modules/generator/__init__.py
Certifik8/modules/generator/certificado.py
Certifik8/modules/handler/__init__.py
Certifik8/modules/handler/tabela.py
Certifik8/modules/selector/__init__.py
Certifik8/modules/selector/file_selection.py
Certifik8/modules/selector/folder_selection.py
Certifik8/modules/utils.py
Certifik8/path.py
Certifik8/tests/__init__.py
Certifik8/tests/test_certificado.py
Certifik8/tests/test_html2pdf.py
Certifik8/tests/test_tabela.py
Certifik8/tests/test_utils.py
certifik8-0.2.4.dist-info/METADATA
certifik8-0.2.4.dist-info/LICENSE
certifik8-0.2.4.dist-info/WHEEL
certifik8-0.2.4.dist-info/entry_points.txt
certifik8-0.2.4.dist-info/RECORD
